LICENSE
MANIFEST.in
README.rst
setup.py
tox.ini
django_sitesutils.egg-info/PKG-INFO
django_sitesutils.egg-info/SOURCES.txt
django_sitesutils.egg-info/dependency_links.txt
django_sitesutils.egg-info/top_level.txt
sitesutils/__init__.py
sitesutils/context_processors.py
sitesutils/helpers.py
sitesutils/middleware.py
tests/__init__.py
tests/runtests.sh
tests/settings.py
tests/test_context_processors/__init__.py
tests/test_context_processors/models.py
tests/test_context_processors/tests.py
tests/test_helpers/__init__.py
tests/test_helpers/models.py
tests/test_helpers/tests.py
tests/test_middleware/__init__.py
tests/test_middleware/models.py
tests/test_middleware/tests.py